rosetta/__init__.py
rosetta/rconverter.py
rosetta/rfaker.py
rosetta/rsender.py
rosetta/constants/__init__.py
rosetta/constants/attributes.py
rosetta/constants/db.py
rosetta/constants/sensors.py
rosetta/constants/sources.py
rosetta/constants/systems.py
rosetta_ce-1.7.5.dist-info/licenses/LICENSE
rosetta_ce-1.7.5.dist-info/METADATA
rosetta_ce-1.7.5.dist-info/WHEEL
rosetta_ce-1.7.5.dist-info/top_level.txt
rosetta_ce-1.7.5.dist-info/RECORD
