Metadata-Version: 2.4
Name: rosetta-ce
Version: 1.7.5
Summary: Rosetta is a Python package that can be used to fake security logs and alerts for testing different detection and response use cases.
Home-page: https://github.com/ayman-m/rosetta
Author: Ayman Mahmoud
Author-email: content@ayman.online
Classifier: Programming Language :: Python :: 3
Classifier: License :: OSI Approved :: MIT License
Classifier: Operating System :: OS Independent
Requires-Python: >=3.6
License-File: LICENSE
Requires-Dist: requests
Requires-Dist: faker
Requires-Dist: urllib3
Dynamic: author
Dynamic: author-email
Dynamic: classifier
Dynamic: description
Dynamic: description-content-type
Dynamic: home-page
Dynamic: license-file
Dynamic: requires-dist
Dynamic: requires-python
Dynamic: summary
